fatsecret/__init__.py
fatsecret/fatsecret.py
fatsecret-0.3.0.dist-info/LICENSE
fatsecret-0.3.0.dist-info/METADATA
fatsecret-0.3.0.dist-info/WHEEL
fatsecret-0.3.0.dist-info/top_level.txt
fatsecret-0.3.0.dist-info/RECORD
