Metadata-Version: 2.1
Name: fatsecret
Version: 0.3.0
Summary: Python wrapper for FatSecret REST API
Home-page: https://github.com/walexnelson/pyfatsecret
Author: Alex Nelson
Author-email: w.alexnelson@gmail.com
License: MIT
Platform: UNKNOWN
Classifier: Development Status :: 4 - Beta
Classifier: Environment :: Console
Classifier: Environment :: Web Environment
Classifier: Intended Audience :: Developers
Classifier: Natural Language :: English
Classifier: License :: OSI Approved :: MIT License
Classifier: Programming Language :: Python
Classifier: Programming Language :: Python :: 2.7
Classifier: Programming Language :: Python :: 3
License-File: LICENSE
Requires-Dist: requests
Requires-Dist: rauth
